albuminer
