Metadata-Version: 1.1
Name: albuminer
Version: 1.2.0
Summary: Tool that, given an audio file or a path with audio files, gets a cover for all of them.
Home-page: https://github.com/unrar/albuminer
Author: unrar
Author-email: joszaynka@gmail.com
License: MIT
Keywords: imagine web internet searching library google images
Platform: UNKNOWN
Classifier: License :: OSI Approved :: MIT License
Classifier: Programming Language :: Python :: 3
